cas_pip/__init__.py
cas_pip/cli.py
cas_pip/casclient/__init__.py
cas_pip/casclient/casclient.py
cas_pip/models/__init__.py
cas_pip/models/lc_pb2.py
cas_pip/models/lc_pb2_grpc.py
cas_pip/models/schema_pb2.py
cas_pip/models/schema_pb2_grpc.py
cas_pip/models/protoc_gen_swagger/__init__.py
cas_pip/models/protoc_gen_swagger/options/__init__.py
cas_pip/models/protoc_gen_swagger/options/annotations_pb2.py
cas_pip/models/protoc_gen_swagger/options/annotations_pb2_grpc.py
cas_pip/models/protoc_gen_swagger/options/openapiv2_pb2.py
cas_pip/models/protoc_gen_swagger/options/openapiv2_pb2_grpc.py
cas_pip-0.1.0.dist-info/LICENSE
cas_pip-0.1.0.dist-info/METADATA
cas_pip-0.1.0.dist-info/WHEEL
cas_pip-0.1.0.dist-info/entry_points.txt
cas_pip-0.1.0.dist-info/top_level.txt
cas_pip-0.1.0.dist-info/RECORD
