Metadata-Version: 2.1
Name: cas-pip
Version: 0.1.0
Summary: Community Attestation pip integration
Home-page: https://github.com/Razikus/cas_pip
Author: Codenotary
License: Apache Software License 2.0
Keywords: cas_pip
Platform: UNKNOWN
Classifier: Development Status :: 3 - Alpha
Classifier: Intended Audience :: Developers
Classifier: License :: OSI Approved :: Apache Software License
Classifier: Natural Language :: English
Classifier: Programming Language :: Python :: 3
Classifier: Programming Language :: Python :: 3.6
Classifier: Programming Language :: Python :: 3.7
Classifier: Programming Language :: Python :: 3.8
Requires-Python: >=3.6
License-File: LICENSE
Requires-Dist: Click (>=8.1.3)
Requires-Dist: grpcio (>=1.44.0)
Requires-Dist: pydantic (>=1.9.0)
Requires-Dist: aiofiles (>=0.8.0)
Requires-Dist: pytz (>=2022.1)
